README.md
setup.py
qmlspectrum/__init__.py
qmlspectrum/bin_spectra.py
qmlspectrum/bin_spectra_old.py
qmlspectrum/ensemble_average.py
qmlspectrum/linalg_solve.py
qmlspectrum/plot_spectrum.py
qmlspectrum/predict.py
qmlspectrum/prepare_trainingdata.py
qmlspectrum/qml_representation.py
qmlspectrum/qml_utils.py
qmlspectrum/read_files.py
qmlspectrum/scores.py
qmlspectrum/shuffle.py
qmlspectrum.egg-info/PKG-INFO
qmlspectrum.egg-info/SOURCES.txt
qmlspectrum.egg-info/dependency_links.txt
qmlspectrum.egg-info/requires.txt
qmlspectrum.egg-info/top_level.txt