Metadata-Version: 1.0
Name: qmlspectrum
Version: 22.4.19
Summary: A test-suite that uses the package qml for modeling continuous spectra
Home-page: https://github.com/raghurama123/qmlspectrum
Author: Raghunathan Ramakrishnan
Author-email: raghu.rama.chem@gmail.com
License: MIT License
Platform: UNKNOWN
